easy_nhl/__init__.py
easy_nhl/base_url.py
easy_nhl/conference.py
easy_nhl/division.py
easy_nhl/game.py
easy_nhl/player.py
easy_nhl/schedule.py
easy_nhl/team.py
easy_nhl-0.3.dist-info/LICENSE
easy_nhl-0.3.dist-info/METADATA
easy_nhl-0.3.dist-info/WHEEL
easy_nhl-0.3.dist-info/top_level.txt
easy_nhl-0.3.dist-info/RECORD
