Metadata-Version: 2.1
Name: easy-nhl
Version: 0.3
Summary: Making it easier to use the NHL API in python projects.
Home-page: https://github.com/branks42/easy-nhl
Author: Justin Branco
Author-email: jbranco@nd.edu
License: MIT
Keywords: hockey,NHL,api,statistics
Platform: UNKNOWN
Classifier: Environment :: Web Environment
Classifier: Intended Audience :: Developers
Classifier: License :: OSI Approved :: BSD License
Classifier: Operating System :: OS Independent
Classifier: Programming Language :: Python
Classifier: Programming Language :: Python :: 3
Classifier: Programming Language :: Python :: 3 :: Only
Classifier: Programming Language :: Python :: 3.6
Classifier: Programming Language :: Python :: 3.7
Classifier: Programming Language :: Python :: 3.8
Classifier: Topic :: Internet :: WWW/HTTP
Classifier: Topic :: Internet :: WWW/HTTP :: Dynamic Content
Requires-Dist: requests (>=2.25.1)
